MANIFEST.in
README.txt
development.ini
ez_setup.py
init.d
setup.cfg
setup.py
test.ini
config/Makefile
config/README
contrib/mantis/021_checkin_user_as_bug_submit_user.patch
contrib/trac/10110_trac_svn_hooks_chgset_date.patch
contrib/trac/10115_trac_svn_hooks_ticket_range.patch
contrib/trac/10116_trac_svn_hooks_fixed_status.patch
docs/index.txt
pySvnManager.egg-info/PKG-INFO
pySvnManager.egg-info/SOURCES.txt
pySvnManager.egg-info/dependency_links.txt
pySvnManager.egg-info/entry_points.txt
pySvnManager.egg-info/not-zip-safe
pySvnManager.egg-info/paste_deploy_config.ini_tmpl
pySvnManager.egg-info/paster_plugins.txt
pySvnManager.egg-info/requires.txt
pySvnManager.egg-info/top_level.txt
pysvnmanager/__init__.py
pysvnmanager/websetup.py
pysvnmanager/config/DefaultConfig.py
pysvnmanager/config/__init__.py
pysvnmanager/config/environment.py
pysvnmanager/config/localconfig.py.in
pysvnmanager/config/middleware.py
pysvnmanager/config/routing.py
pysvnmanager/config/svn.access.in
pysvnmanager/config/svn.passwd.in
pysvnmanager/controllers/__init__.py
pysvnmanager/controllers/authz.py
pysvnmanager/controllers/check.py
pysvnmanager/controllers/error.py
pysvnmanager/controllers/logs.py
pysvnmanager/controllers/repos.py
pysvnmanager/controllers/role.py
pysvnmanager/controllers/security.py
pysvnmanager/controllers/template.py
pysvnmanager/hooks/__init__.py
pysvnmanager/hooks/init/__init__.py
pysvnmanager/hooks/init/hook1.4/parse_ini.sh
pysvnmanager/hooks/init/hook1.4/post-commit
pysvnmanager/hooks/init/hook1.4/post-lock.tmpl
pysvnmanager/hooks/init/hook1.4/post-revprop-change
pysvnmanager/hooks/init/hook1.4/post-unlock.tmpl
pysvnmanager/hooks/init/hook1.4/pre-commit
pysvnmanager/hooks/init/hook1.4/pre-lock.tmpl
pysvnmanager/hooks/init/hook1.4/pre-revprop-change
pysvnmanager/hooks/init/hook1.4/pre-unlock.tmpl
pysvnmanager/hooks/init/hook1.4/start-commit
pysvnmanager/hooks/init/hook1.4/scripts/README
pysvnmanager/hooks/init/hook1.4/scripts/check-authz.py
pysvnmanager/hooks/init/hook1.4/scripts/check-case-insensitive.pl
pysvnmanager/hooks/init/hook1.4/scripts/check-case-insensitive.py
pysvnmanager/hooks/init/hook1.4/scripts/check-mime-type.pl
pysvnmanager/hooks/init/hook1.4/scripts/check-mime-type.py
pysvnmanager/hooks/init/hook1.4/scripts/commit-access-control.cfg
