Metadata-Version: 1.0
Name: pySvnManager
Version: 0.3.0dev-r80
Summary: SVN authz web management tools.
Home-page: https://sourceforge.net/projects/pysvnmanager
Author: Jiang Xin
Author-email: jiangxin@ossxp.com
License: UNKNOWN
Platform: UNKNOWN
